{
    "4026 B.C.E.": {
        "year": "4026",
        "isCE": false
    },
    "a. 4026 B.C.E.": {
        "prefix": "a.",
        "year": "4026",
        "isCE": false
    },
    "b. 3896 B.C.E.": {
        "prefix": "b.",
        "year": "3896",
        "isCE": false
    },
    "3896 B.C.E.": {
        "year": "3896",
        "isCE": false
    },
    "3404 B.C.E.": {
        "year": "3404",
        "isCE": false
    },
    "3339 B.C.E.": {
        "year": "3339",
        "isCE": false
    },
    "3152 B.C.E.": {
        "year": "3152",
        "isCE": false
    },
    "3096 B.C.E.": {
        "year": "3096",
        "isCE": false
    },
    "3039 B.C.E.": {
        "year": "3039",
        "isCE": false
    },
    "2970 B.C.E.": {
        "year": "2970",
        "isCE": false
    },
    "2490 B.C.E.": {
        "year": "2490",
        "isCE": false
    },
    "2470 B.C.E.": {
        "year": "2470",
        "isCE": false
    },
    "2468 B.C.E.": {
        "year": "2468",
        "isCE": false
    },
    "2370 B.C.E.": {
        "year": "2370",
        "isCE": false
    },
    "2370 B.C.E.-a": {
        "year": "2370",
        "isCE": false
    },
    "2369 B.C.E.": {
        "year": "2369",
        "isCE": false
    },
    "2368 B.C.E.": {
        "year": "2368",
        "isCE": false
    },
    "a. 2269 B.C.E.": {
        "prefix": "a.",
        "year": "2269",
        "isCE": false
    },
    "2020 B.C.E.": {
        "year": "2020",
        "isCE": false
    },
    "2018 B.C.E.": {
        "year": "2018",
        "isCE": false
    },
    "1943 B.C.E.": {
        "year": "1943",
        "isCE": false
    },
    "b. 1933 B.C.E.": {
        "prefix": "b.",
        "year": "1933",
        "isCE": false
    },
    "1932 B.C.E.": {
        "year": "1932",
        "isCE": false
    },
    "1919 B.C.E.": {
        "year": "1919",
        "isCE": false
    },
    "1919 B.C.E.-a": {
        "year": "1919",
        "isCE": false
    },
    "1918 B.C.E.": {
        "year": "1918",
        "isCE": false
    },
    "1913 B.C.E.": {
        "year": "1913",
        "isCE": false
    },
    "1881 B.C.E.": {
        "year": "1881",
        "isCE": false
    },
    "1878 B.C.E.": {
        "year": "1878",
        "isCE": false
    },
    "1868 B.C.E.": {
        "year": "1868",
        "isCE": false
    },
    "1858 B.C.E.": {
        "year": "1858",
        "isCE": false
    },
    "1843 B.C.E.": {
        "year": "1843",
        "isCE": false
    },
    "1818 B.C.E.": {
        "year": "1818",
        "isCE": false
    },
    "1795 B.C.E.": {
        "year": "1795",
        "isCE": false
    },
    "1781 B.C.E.": {
        "year": "1781",
        "isCE": false
    },
    "1774 B.C.E.": {
        "year": "1774",
        "isCE": false
    },
    "1767 B.C.E.": {
        "year": "1767",
        "isCE": false
    },
    "1761 B.C.E.": {
        "year": "1761",
        "isCE": false
    },
    "c. 1761 B.C.E.": {
        "prefix": "c.",
        "year": "1761",
        "isCE": false
    },
    "1750 B.C.E.": {
        "year": "1750",
        "isCE": false
    },
    "1738 B.C.E.": {
        "year": "1738",
        "isCE": false
    },
    "1737 B.C.E.": {
        "year": "1737",
        "isCE": false
    },
    "1728 B.C.E.": {
        "year": "1728",
        "isCE": false
    },
    "1711 B.C.E.": {
        "year": "1711",
        "isCE": false
    },
    "1657 B.C.E.": {
        "year": "1657",
        "isCE": false
    },
    "b. 1613 B.C.E.": {
        "prefix": "b.",
        "year": "1613",
        "isCE": false
    },
    "a. 1600 B.C.E.": {
        "prefix": "a.",
        "year": "1600",
        "isCE": false
    },
    "1593 B.C.E.": {
        "year": "1593",
        "isCE": false
    },
    "1553 B.C.E.": {
        "year": "1553",
        "isCE": false
    },
    "c. 1514 B.C.E.": {
        "prefix": "c.",
        "year": "1514",
        "isCE": false
    },
    "1513 B.C.E.-a": {
        "year": "1513",
        "isCE": false
    },
    "1513 B.C.E.-d": {
        "year": "1513",
        "isCE": false
    },
    "1513 B.C.E.-b": {
        "year": "1513",
        "isCE": false
    },
    "1513 B.C.E.-e": {
        "year": "1513",
        "isCE": false
    },
    "1513 B.C.E.-c": {
        "year": "1513",
        "isCE": false
    },
    "1512 B.C.E.-a": {
        "year": "1512",
        "isCE": false
    },
    "1512 B.C.E.-b": {
        "year": "1512",
        "isCE": false
    },
    "1512 B.C.E.-c": {
        "year": "1512",
        "isCE": false
    },
    "1473 B.C.E.-a": {
        "year": "1473",
        "isCE": false
    },
    "c. 1473 B.C.E.": {
        "prefix": "c.",
        "year": "1473",
        "isCE": false
    },
    "1473 B.C.E.-c": {
        "year": "1473",
        "isCE": false
    },
    "1473 B.C.E.-b": {
        "year": "1473",
        "isCE": false
    },
    "1473 B.C.E.-d": {
        "year": "1473",
        "isCE": false
    },
    "1473 B.C.E.-e": {
        "year": "1473",
        "isCE": false
    },
    "1467 B.C.E.": {
        "year": "1467",
        "isCE": false
    },
    "c. 1450 B.C.E.-a": {
        "prefix": "c.",
        "year": "1450",
        "isCE": false
    },
    "c. 1450 B.C.E.-b": {
        "prefix": "c.",
        "year": "1450",
        "isCE": false
    },
    "1117 B.C.E.": {
        "year": "1117",
        "isCE": false
    },
    "1107 B.C.E.": {
        "year": "1107",
        "isCE": false
    },
    "c. 1100 B.C.E.": {
        "prefix": "c.",
        "year": "1100",
        "isCE": false
    },
    "c. 1090 B.C.E.": {
        "prefix": "c.",
        "year": "1090",
        "isCE": false
    },
    "c. 1078 B.C.E.": {
        "prefix": "c.",
        "year": "1078",
        "isCE": false
    },
    "1077 B.C.E.": {
        "year": "1077",
        "isCE": false
    },
    "1070 B.C.E.": {
        "year": "1070",
        "isCE": false
    },
    "a. 1070 B.C.E.": {
        "prefix": "a.",
        "year": "1070",
        "isCE": false
    },
    "c. 1040 B.C.E.": {
        "prefix": "c.",
        "year": "1040",
        "isCE": false
    },
    "1037 B.C.E.": {
        "year": "1037",
        "isCE": false
    },
    "1034 B.C.E.": {
        "year": "1034",
        "isCE": false
    },
    "1027 B.C.E.": {
        "year": "1027",
        "isCE": false
    },
    "c. 1020 B.C.E.": {
        "prefix": "c.",
        "year": "1020",
        "isCE": false
    },
    "b. 1000 B.C.E.": {
        "prefix": "b.",
        "year": "1000",
        "isCE": false
    },
    "997 B.C.E.": {
        "year": "997",
        "isCE": false
    },
    "993 B.C.E.": {
        "year": "993",
        "isCE": false
    },
    "980 B.C.E.": {
        "year": "980",
        "isCE": false
    },
    "977 B.C.E.": {
        "year": "977",
        "isCE": false
    },
    "c. 976 B.C.E.": {
        "prefix": "c.",
        "year": "976",
        "isCE": false
    },
    "c. 975 B.C.E.": {
        "prefix": "c.",
        "year": "975",
        "isCE": false
    },
    "c. 952 B.C.E.": {
        "prefix": "c.",
        "year": "952",
        "isCE": false
    },
    "c. 951 B.C.E.-a": {
        "prefix": "c.",
        "year": "951",
        "isCE": false
    },
    "c. 951 B.C.E.-b": {
        "prefix": "c.",
        "year": "951",
        "isCE": false
    },
    "c. 947 B.C.E.": {
        "prefix": "c.",
        "year": "947",
        "isCE": false
    },
    "c. 940 B.C.E.": {
        "prefix": "c.",
        "year": "940",
        "isCE": false
    },
    "936 B.C.E.": {
        "year": "936",
        "isCE": false
    },
    "c. 919 B.C.E.": {
        "prefix": "c.",
        "year": "919",
        "isCE": false
    },
    "c. 917 B.C.E.": {
        "prefix": "c.",
        "year": "917",
        "isCE": false
    },
    "913 B.C.E.": {
        "year": "913",
        "isCE": false
    },
    "c. 906 B.C.E.": {
        "prefix": "c.",
        "year": "906",
        "isCE": false
    },
    "c. 905 B.C.E.-a": {
        "prefix": "c.",
        "year": "905",
        "isCE": false
    },
    "c. 905 B.C.E.-b": {
        "prefix": "c.",
        "year": "905",
        "isCE": false
    },
    "898 B.C.E.": {
        "year": "898",
        "isCE": false
    },
    "876 B.C.E.": {
        "year": "876",
        "isCE": false
    },
    "c. 859 B.C.E.": {
        "prefix": "c.",
        "year": "859",
        "isCE": false
    },
    "858 B.C.E.": {
        "year": "858",
        "isCE": false
    },
    "c. 844 B.C.E.-a": {
        "prefix": "c.",
        "year": "844",
        "isCE": false
    },
    "c. 844 B.C.E.-b": {
        "prefix": "c.",
        "year": "844",
        "isCE": false
    },
    "829 B.C.E.": {
        "year": "829",
        "isCE": false
    },
    "c. 820 B.C.E.": {
        "prefix": "c.",
        "year": "820",
        "isCE": false
    },
    "c. 804 B.C.E.": {
        "prefix": "c.",
        "year": "804",
        "isCE": false
    },
    "c. 792 B.C.E.": {
        "prefix": "c.",
        "year": "792",
        "isCE": false
    },
    "c. 791 B.C.E.": {
        "prefix": "c.",
        "year": "791",
        "isCE": false
    },
    "c. 780 B.C.E.": {
        "prefix": "c.",
        "year": "780",
        "isCE": false
    },
    "c. 778 B.C.E.": {
        "prefix": "c.",
        "year": "778",
        "isCE": false
    },
    "777 B.C.E.": {
        "year": "777",
        "isCE": false
    },
    "c. 761 B.C.E.": {
        "prefix": "c.",
        "year": "761",
        "isCE": false
    },
    "c. 758 B.C.E.": {
        "prefix": "c.",
        "year": "758",
        "isCE": false
    },
    "745 B.C.E.": {
        "year": "745",
        "isCE": false
    },
    "a. 745 B.C.E.": {
        "prefix": "a.",
        "year": "745",
        "isCE": false
    },
    "740 B.C.E.": {
        "year": "740",
        "isCE": false
    },
    "732 B.C.E.": {
        "year": "732",
        "isCE": false
    },
    "a. 732 B.C.E.": {
        "prefix": "a.",
        "year": "732",
        "isCE": false
    },
    "b. 717 B.C.E.": {
        "prefix": "b.",
        "year": "717",
        "isCE": false
    },
    "c. 717 B.C.E.": {
        "prefix": "c.",
        "year": "717",
        "isCE": false
    },
    "716 B.C.E.": {
        "year": "716",
        "isCE": false
    },
    "661 B.C.E.": {
        "year": "661",
        "isCE": false
    },
    "659 B.C.E.": {
        "year": "659",
        "isCE": false
    },
    "b. 648 B.C.E.": {
        "prefix": "b.",
        "year": "648",
        "isCE": false
    },
    "647 B.C.E.": {
        "year": "647",
        "isCE": false
    },
    "b. 632 B.C.E.": {
        "prefix": "b.",
        "year": "632",
        "isCE": false
    },
    "632 B.C.E.": {
        "year": "632",
        "isCE": false
    },
    "628 B.C.E.-a": {
        "year": "628",
        "isCE": false
    },
    "628 B.C.E.-b": {
        "year": "628",
        "isCE": false
    },
    "c. 628 B.C.E.": {
        "prefix": "c.",
        "year": "628",
        "isCE": false
    },
    "625 B.C.E.": {
        "year": "625",
        "isCE": false
    },
    "620 B.C.E.": {
        "year": "620",
        "isCE": false
    },
    "618 B.C.E.": {
        "year": "618",
        "isCE": false
    },
    "617 B.C.E.": {
        "year": "617",
        "isCE": false
    },
    "613 B.C.E.": {
        "year": "613",
        "isCE": false
    },
    "609 B.C.E.": {
        "year": "609",
        "isCE": false
    },
    "607 B.C.E.-a": {
        "year": "607",
        "isCE": false
    },
    "607 B.C.E.-b": {
        "year": "607",
        "isCE": false
    },
    "607 B.C.E.-c": {
        "year": "607",
        "isCE": false
    },
    "c. 607 B.C.E.": {
        "prefix": "c.",
        "year": "607",
        "isCE": false
    },
    "c. 591 B.C.E.": {
        "prefix": "c.",
        "year": "591",
        "isCE": false
    },
    "580 B.C.E.": {
        "year": "580",
        "isCE": false
    },
    "539 B.C.E.": {
        "year": "539",
        "isCE": false
    },
    "537 B.C.E.": {
        "year": "537",
        "isCE": false
    },
    "c. 536 B.C.E.": {
        "prefix": "c.",
        "year": "536",
        "isCE": false
    },
    "536 B.C.E.": {
        "year": "536",
        "isCE": false
    },
    "522 B.C.E.": {
        "year": "522",
        "isCE": false
    },
    "520 B.C.E.": {
        "year": "520",
        "isCE": false
    },
    "518 B.C.E.": {
        "year": "518",
        "isCE": false
    },
    "515 B.C.E.": {
        "year": "515",
        "isCE": false
    },
    "c. 475 B.C.E.": {
        "prefix": "c.",
        "year": "475",
        "isCE": false
    },
    "468 B.C.E.": {
        "year": "468",
        "isCE": false
    },
    "c. 460 B.C.E.": {
        "prefix": "c.",
        "year": "460",
        "isCE": false
    },
    "455 B.C.E.-a": {
        "year": "455",
        "isCE": false
    },
    "455 B.C.E.-b": {
        "year": "455",
        "isCE": false
    },
    "a. 443 B.C.E.-a": {
        "prefix": "a.",
        "year": "443",
        "isCE": false
    },
    "a. 443 B.C.E.-b": {
        "prefix": "a.",
        "year": "443",
        "isCE": false
    },
    "406 B.C.E.": {
        "year": "406",
        "isCE": false
    },
    "332 B.C.E.": {
        "year": "332",
        "isCE": false
    },
    "c. 280 B.C.E.": {
        "prefix": "c.",
        "year": "280",
        "isCE": false
    },
    "165 B.C.E.": {
        "year": "165",
        "isCE": false
    },
    "63 B.C.E.": {
        "year": "63",
        "isCE": false
    },
    "c. 37 B.C.E.": {
        "prefix": "c.",
        "year": "37",
        "isCE": false
    },
    "2 B.C.E.": {
        "year": "2",
        "isCE": false
    },
    "29 C.E.": {
        "year": "29",
        "isCE": true
    },
    "33 C.E.-a": {
        "year": "33",
        "isCE": true
    },
    "33 C.E.-b": {
        "year": "33",
        "isCE": true
    },
    "33 C.E.-c": {
        "year": "33",
        "isCE": true
    },
    "36 C.E.": {
        "year": "36",
        "isCE": true
    },
    "c. 47-48 C.E.": {
        "prefix": "c.",
        "year": "47-48",
        "isCE": true
    },
    "c. 49 C.E.": {
        "prefix": "c.",
        "year": "49",
        "isCE": true
    },
    "c. 49-52 C.E.": {
        "prefix": "c.",
        "year": "49-52",
        "isCE": true
    },
    "c. 52-56 C.E.": {
        "prefix": "c.",
        "year": "52-56",
        "isCE": true
    },
    "c. 98 C.E.-a": {
        "prefix": "c.",
        "year": "98",
        "isCE": true
    },
    "c. 98 C.E.-c": {
        "prefix": "c.",
        "year": "98",
        "isCE": true
    },
    "c. 100 C.E.": {
        "prefix": "c.",
        "year": "100",
        "isCE": true
    },
    "1513 B.C.E.-z": {
        "year": "1513",
        "isCE": false
    },
    "1512 B.C.E.-z": {
        "year": "1512",
        "isCE": false
    },
    "1512 B.C.E.-y": {
        "year": "1512",
        "isCE": false
    },
    "1473 B.C.E.-z": {
        "year": "1473",
        "isCE": false
    },
    "1473 B.C.E.-y": {
        "year": "1473",
        "isCE": false
    },
    "c. 1450 B.C.E.-z": {
        "prefix": "c.",
        "year": "1450",
        "isCE": false
    },
    "c. 1100 B.C.E.-z": {
        "prefix": "c.",
        "year": "1100",
        "isCE": false
    },
    "c. 1090 B.C.E.-z": {
        "prefix": "c.",
        "year": "1090",
        "isCE": false
    },
    "c. 1078 B.C.E.-z": {
        "prefix": "c.",
        "year": "1078",
        "isCE": false
    },
    "c. 1040 B.C.E.-z": {
        "prefix": "c.",
        "year": "1040",
        "isCE": false
    },
    "580 B.C.E.-z": {
        "year": "580",
        "isCE": false
    },
    "580 B.C.E.-y": {
        "year": "580",
        "isCE": false
    },
    "c. 460 B.C.E.-z": {
        "prefix": "c.",
        "year": "460",
        "isCE": false
    },
    "c. 460 B.C.E.-y": {
        "prefix": "c.",
        "year": "460",
        "isCE": false
    },
    "c. 460 B.C.E.-x": {
        "prefix": "c.",
        "year": "460",
        "isCE": false
    },
    "a. 443 B.C.E.-z": {
        "prefix": "a.",
        "year": "443",
        "isCE": false
    },
    "c. 475 B.C.E.-z": {
        "prefix": "c.",
        "year": "475",
        "isCE": false
    },
    "c. 1473 B.C.E.-z": {
        "prefix": "c.",
        "year": "1473",
        "isCE": false
    },
    "c. 460 B.C.E.-w": {
        "prefix": "c.",
        "year": "460",
        "isCE": false
    },
    "c. 717 B.C.E.-z": {
        "prefix": "c.",
        "year": "717",
        "isCE": false
    },
    "b. 1000 B.C.E.-z": {
        "prefix": "b.",
        "year": "1000",
        "isCE": false
    },
    "c. 1020 B.C.E.-z": {
        "prefix": "c.",
        "year": "1020",
        "isCE": false
    },
    "a. 732 B.C.E.-z": {
        "prefix": "a.",
        "year": "732",
        "isCE": false
    },
    "580 B.C.E.-x": {
        "year": "580",
        "isCE": false
    },
    "607 B.C.E.-z": {
        "year": "607",
        "isCE": false
    },
    "c. 591 B.C.E.-z": {
        "prefix": "c.",
        "year": "591",
        "isCE": false
    },
    "c. 536 B.C.E.-z": {
        "prefix": "c.",
        "year": "536",
        "isCE": false
    },
    "a. 745 B.C.E.-z": {
        "prefix": "a.",
        "year": "745",
        "isCE": false
    },
    "c. 820 (?) B.C.E.-z": {
        "prefix": "c.",
        "year": "820 (?)",
        "isCE": false
    },
    "c. 804 B.C.E.-z": {
        "prefix": "c.",
        "year": "804",
        "isCE": false
    },
    "c. 607 B.C.E.-z": {
        "prefix": "c.",
        "year": "607",
        "isCE": false
    },
    "c. 844 B.C.E.-z": {
        "prefix": "c.",
        "year": "844",
        "isCE": false
    },
    "b. 717 B.C.E.-z": {
        "prefix": "b.",
        "year": "717",
        "isCE": false
    },
    "b. 632 B.C.E.-z": {
        "prefix": "b.",
        "year": "632",
        "isCE": false
    },
    "c. 628 (?) B.C.E.-z": {
        "prefix": "c.",
        "year": "628 (?)",
        "isCE": false
    },
    "b. 648 B.C.E.-z": {
        "prefix": "b.",
        "year": "648",
        "isCE": false
    },
    "520 B.C.E.-z": {
        "year": "520",
        "isCE": false
    },
    "518 B.C.E.-z": {
        "year": "518",
        "isCE": false
    },
    "a. 443 B.C.E.-y": {
        "prefix": "a.",
        "year": "443",
        "isCE": false
    },
    "c. 41 C.E.-z": {
        "prefix": "c.",
        "year": "41",
        "isCE": true
    },
    "c. 60-65 C.E.-z": {
        "prefix": "c.",
        "year": "60-65",
        "isCE": true
    },
    "c. 56-58 C.E.-z": {
        "prefix": "c.",
        "year": "56-58",
        "isCE": true
    },
    "c. 98 C.E.-z": {
        "prefix": "c.",
        "year": "98",
        "isCE": true
    },
    "c. 61 C.E.-z": {
        "prefix": "c.",
        "year": "61",
        "isCE": true
    },
    "c. 56 C.E.-z": {
        "prefix": "c.",
        "year": "56",
        "isCE": true
    },
    "c. 55 C.E.-z": {
        "prefix": "c.",
        "year": "55",
        "isCE": true
    },
    "c. 55 C.E.-y": {
        "prefix": "c.",
        "year": "55",
        "isCE": true
    },
    "c. 50-52 C.E.-z": {
        "prefix": "c.",
        "year": "50-52",
        "isCE": true
    },
    "c. 60-61 C.E.-z": {
        "prefix": "c.",
        "year": "60-61",
        "isCE": true
    },
    "c. 60-61 C.E.-y": {
        "prefix": "c.",
        "year": "60-61",
        "isCE": true
    },
    "c. 60-61 C.E.-x": {
        "prefix": "c.",
        "year": "60-61",
        "isCE": true
    },
    "c. 50 C.E.-z": {
        "prefix": "c.",
        "year": "50",
        "isCE": true
    },
    "c. 51 C.E.-z": {
        "prefix": "c.",
        "year": "51",
        "isCE": true
    },
    "c. 61-64 C.E.-z": {
        "prefix": "c.",
        "year": "61-64",
        "isCE": true
    },
    "c. 65 C.E.-z": {
        "prefix": "c.",
        "year": "65",
        "isCE": true
    },
    "c. 61-64 C.E.-y": {
        "prefix": "c.",
        "year": "61-64",
        "isCE": true
    },
    "c. 60-61 C.E.-w": {
        "prefix": "c.",
        "year": "60-61",
        "isCE": true
    },
    "c. 61 C.E.-y": {
        "prefix": "c.",
        "year": "61",
        "isCE": true
    },
    "b. 62 C.E.-z": {
        "prefix": "b.",
        "year": "62",
        "isCE": true
    },
    "c. 62-64 C.E.-z": {
        "prefix": "c.",
        "year": "62-64",
        "isCE": true
    },
    "c. 64 C.E.-z": {
        "prefix": "c.",
        "year": "64",
        "isCE": true
    },
    "c. 98 C.E.-y": {
        "prefix": "c.",
        "year": "98",
        "isCE": true
    },
    "c. 98 C.E.-x": {
        "prefix": "c.",
        "year": "98",
        "isCE": true
    },
    "c. 98 C.E.-w": {
        "prefix": "c.",
        "year": "98",
        "isCE": true
    },
    "c. 65 C.E.-y": {
        "prefix": "c.",
        "year": "65",
        "isCE": true
    },
    "c. 96 C.E.-z": {
        "prefix": "c.",
        "year": "96",
        "isCE": true
    }
}